stomics3d/__init__.py
stomics3d/app.py
stomics3d/dashapp_3dviewer.py
stomics3d-0.1.2.dist-info/LICENSE
stomics3d-0.1.2.dist-info/METADATA
stomics3d-0.1.2.dist-info/WHEEL
stomics3d-0.1.2.dist-info/entry_points.txt
stomics3d-0.1.2.dist-info/top_level.txt
stomics3d-0.1.2.dist-info/RECORD
